LICENSE
MANIFEST.in
README.rst
setup.py
django_sysadmin/__init__.py
django_sysadmin.egg-info/PKG-INFO
django_sysadmin.egg-info/SOURCES.txt
django_sysadmin.egg-info/dependency_links.txt
django_sysadmin.egg-info/not-zip-safe
django_sysadmin.egg-info/requires.txt
django_sysadmin.egg-info/top_level.txt
django_sysadmin/postfix/__init__.py
django_sysadmin/postfix/admin.py
django_sysadmin/postfix/models.py
django_sysadmin/postfix/tests.py
django_sysadmin/postfix/views.py
django_sysadmin/proftpd/__init__.py
django_sysadmin/proftpd/admin.py
django_sysadmin/proftpd/models.py
django_sysadmin/proftpd/tests.py
django_sysadmin/proftpd/views.py
sample-config/postfix/main.cf
sample-config/postfix/virtual_alias_maps.cf
sample-config/postfix/virtual_mailbox_domains.cf
sample-config/postfix/virtual_mailbox_maps.cf
sample-config/postfix/sasl/smtpd.conf
sample-config/proftpd/sql.conf