Metadata-Version: 1.0
Name: django-sysadmin
Version: 0.3
Summary: Django models to make a sysadmins life easier
Home-page: https://github.com/bmaeser/django-sysadmin
Author: Bernhard Maeser
Author-email: bernhard.maeser@gmail.com
License: MIT
Platform: UNKNOWN
Classifier: Development Status :: 5 - Production/Stable
Classifier: Intended Audience :: System Administrators
Classifier: Topic :: System :: Systems Administration
Classifier: Topic :: System :: Installation/Setup
Classifier: Operating System :: POSIX
Classifier: License :: OSI Approved :: MIT License
Classifier: Programming Language :: Python
Classifier: Programming Language :: Python :: 2.5
Classifier: Programming Language :: Python :: 2.6
Classifier: Programming Language :: Python :: 2.7
